video_vit/__init__.py
video_vit/main.py
video_vit-0.0.4.dist-info/LICENSE
video_vit-0.0.4.dist-info/WHEEL
video_vit-0.0.4.dist-info/entry_points.txt
video_vit-0.0.4.dist-info/METADATA
video_vit-0.0.4.dist-info/RECORD
